odoo/addons/pos_product_mergeable_line/README.rst
odoo/addons/pos_product_mergeable_line/__init__.py
odoo/addons/pos_product_mergeable_line/__manifest__.py
odoo/addons/pos_product_mergeable_line/i18n/fr.po
odoo/addons/pos_product_mergeable_line/i18n/pos_product_mergeable_line.pot
odoo/addons/pos_product_mergeable_line/models/__init__.py
odoo/addons/pos_product_mergeable_line/models/product_template.py
odoo/addons/pos_product_mergeable_line/readme/CONTRIBUTORS.rst
odoo/addons/pos_product_mergeable_line/readme/DESCRIPTION.rst
odoo/addons/pos_product_mergeable_line/static/description/icon.png
odoo/addons/pos_product_mergeable_line/static/description/index.html
odoo/addons/pos_product_mergeable_line/static/src/js/models.js
odoo/addons/pos_product_mergeable_line/views/templates.xml
odoo/addons/pos_product_mergeable_line/views/view_product_template.xml
odoo12_addon_pos_product_mergeable_line-12.0.1.0.2.dist-info/METADATA
odoo12_addon_pos_product_mergeable_line-12.0.1.0.2.dist-info/WHEEL
odoo12_addon_pos_product_mergeable_line-12.0.1.0.2.dist-info/top_level.txt
odoo12_addon_pos_product_mergeable_line-12.0.1.0.2.dist-info/RECORD
